imagelibz/SegIEPolys.py
imagelibz/__init__.py
imagelibz/blursharpen.py
imagelibz/color_transfer.py
imagelibz/common.py
imagelibz/draw.py
imagelibz/equalize_and_stack_square.py
imagelibz/estimate_sharpness.py
imagelibz/filters.py
imagelibz/morph.py
imagelibz/randomex.py
imagelibz/reduce_colors.py
imagelibz/warp.py
imagelibz/sd/__init__.py
imagelibz/sd/calc.py
imagelibz/sd/draw.py
imagelibz-0.0.2.dist-info/LICENSE
imagelibz-0.0.2.dist-info/METADATA
imagelibz-0.0.2.dist-info/WHEEL
imagelibz-0.0.2.dist-info/top_level.txt
imagelibz-0.0.2.dist-info/RECORD
